stroom/__init__.py
stroom-0.0.1.dev1.dist-info/LICENSE
stroom-0.0.1.dev1.dist-info/METADATA
stroom-0.0.1.dev1.dist-info/WHEEL
stroom-0.0.1.dev1.dist-info/top_level.txt
stroom-0.0.1.dev1.dist-info/RECORD
